qsppack/__init__.py
qsppack/nlfa.py
qsppack/objective.py
qsppack/optimizers.py
qsppack/solver.py
qsppack/utils.py
qsppack-0.3.12.dist-info/METADATA
qsppack-0.3.12.dist-info/WHEEL
qsppack-0.3.12.dist-info/top_level.txt
qsppack-0.3.12.dist-info/RECORD
